tukan_python/__init__.py
tukan_python/query.py
tukan_python/tukan.py
tukan_python-0.2.0.dist-info/licenses/LICENSE
tukan_python-0.2.0.dist-info/METADATA
tukan_python-0.2.0.dist-info/WHEEL
tukan_python-0.2.0.dist-info/top_level.txt
tukan_python-0.2.0.dist-info/RECORD
