Metadata-Version: 2.4
Name: tukan_python
Version: 0.2.0
Summary: SDK de Python para acceder a datos oficiales de México a través de la API de Tukan.
Author-email: TukanMx <contacto@tukanmx.com>
License-Expression: MIT
Project-URL: Homepage, https://tukanmx.com
Project-URL: Repository, https://github.com/TukanMx/tukan_python
Project-URL: Documentation, https://github.com/TukanMx/tukan_python#readme
Keywords: tukan,mexico,data,api,inegi,banxico,cnbv,analytics
Classifier: Development Status :: 4 - Beta
Classifier: Intended Audience :: Developers
Classifier: Intended Audience :: Science/Research
Classifier: Programming Language :: Python :: 3
Classifier: Programming Language :: Python :: 3.9
Classifier: Programming Language :: Python :: 3.10
Classifier: Programming Language :: Python :: 3.11
Classifier: Programming Language :: Python :: 3.12
Classifier: Operating System :: OS Independent
Classifier: Topic :: Scientific/Engineering :: Information Analysis
Requires-Python: >=3.9
License-File: LICENSE
Requires-Dist: pandas>=1.5.0
Requires-Dist: requests>=2.28.0
Requires-Dist: python-dotenv>=1.0.0
Dynamic: license-file
